hedayat_media/__init__.py
hedayat_media/core.py
hedayat_media/maddahi.py
hedayat_media/data/hadiths.json
hedayat_media-1.6.6.dist-info/METADATA
hedayat_media-1.6.6.dist-info/WHEEL
hedayat_media-1.6.6.dist-info/top_level.txt
hedayat_media-1.6.6.dist-info/RECORD
