Metadata-Version: 2.1
Name: hedayat-media
Version: 1.6.6
Summary: یک کتابخانه جامع برای دسترسی به احادیث، قرآن، ذکر و اطلاعات جغرافیایی مساجد
Home-page: https://github.com/amirhossinpython/hedayat_media
Author: امیرحسین خزاعی
Author-email: amirhossinpython03@gmail.com
Classifier: Programming Language :: Python :: 3
Classifier: License :: OSI Approved :: MIT License
Classifier: Operating System :: OS Independent
Classifier: Intended Audience :: Developers
Classifier: Topic :: Software Development :: Libraries :: Python Modules
Requires-Python: >=3.8
Requires-Dist: requests>=2.28.0
Requires-Dist: deep-translator>=1.8.1
Requires-Dist: geopy>=2.3.0
Requires-Dist: openai
Requires-Dist: httpx
Requires-Dist: beautifulsoup4
